dwd_opendata_get_grib.py
dwd_opendata_get_grib-0.0.6.dist-info/LICENSE
dwd_opendata_get_grib-0.0.6.dist-info/METADATA
dwd_opendata_get_grib-0.0.6.dist-info/WHEEL
dwd_opendata_get_grib-0.0.6.dist-info/entry_points.txt
dwd_opendata_get_grib-0.0.6.dist-info/top_level.txt
dwd_opendata_get_grib-0.0.6.dist-info/RECORD
