Metadata-Version: 2.1
Name: dwd-opendata-get-grib
Version: 0.0.6
Summary: Script to download grib2 data and converting it into other data format for wider usage
Author-email: Dogukan Mertoglu <dogukan.mertoglu01@gmail.com>
Maintainer-email: Dogukan Mertoglu <dogukan.mertoglu01@gmail.com>
License: Copyright (c) 2023 Dogukan Mertoglu
Project-URL: Homepage, https://github.com/dokick/dwd-opendata-get-grib
Project-URL: Repository, https://github.com/dokick/dwd-opendata-get-grib
Keywords: grib,dwd,opendata,weather,eccodes
Classifier: License :: OSI Approved :: MIT License
Classifier: Programming Language :: Python :: 3
Classifier: Programming Language :: Python :: 3 :: Only
Classifier: Programming Language :: Python :: 3.8
Classifier: Programming Language :: Python :: 3.9
Classifier: Programming Language :: Python :: 3.10
Classifier: Programming Language :: Python :: 3.11
Classifier: Programming Language :: Python :: 3.12
Classifier: Typing :: Typed
Requires-Python: >=3.8
License-File: LICENSE
Requires-Dist: eccodes
Requires-Dist: httpx
Requires-Dist: numpy
Requires-Dist: pandas
Provides-Extra: conda
Requires-Dist: tox-conda ; extra == 'conda'
Provides-Extra: dev
Requires-Dist: coverage >=7 ; extra == 'dev'
Requires-Dist: isort >=5 ; extra == 'dev'
Requires-Dist: pandas-stubs ; extra == 'dev'
Requires-Dist: pylint >=3 ; extra == 'dev'
Requires-Dist: pytest >=7 ; extra == 'dev'
Requires-Dist: tox >=3 ; extra == 'dev'
